[{"Last Update Time CE": "10:56:02", "Symbol CE": "NFO:BANKNIFTY2431347000CE", "LTP CE": "0.0", "RSI 5M CE": "36.19", "RSI 10M CE": "31.71", "RSI 15M CE": "33.29", "VWAP 5M CE": "763.96", "VWAP 10M CE": "764.49", "VWAP 15M CE": "770.17", "EMA 5M CE": "757.55", "EMA 10M CE": "799.76", "EMA 15M CE": "843.89", "ST 5M CE": "835.57", "ST 10M CE": "894.84", "ST 15M CE": "973.13", "Strike": "47000.0", "Last Update Time PE": "10:56:03", "Symbol PE": "NFO:BANKNIFTY2431347000PE", "LTP PE": "0.0", "RSI 5M PE": "45.63", "RSI 10M PE": "44.49", "RSI 15M PE": "43.61", "VWAP 5M PE": "102.59", "VWAP 10M PE": "102.54", "VWAP 15M PE": "103.59", "EMA 5M PE": "98.68", "EMA 10M PE": "99.79", "EMA 15M PE": "102.98", "ST 5M PE": "78.7", "ST 10M PE": "120.94", "ST 15M PE": "133.25"}, {"Last Update Time CE": "10:56:04", "Symbol CE": "NFO:BANKNIFTY2431347100CE", "LTP CE": "0.0", "RSI 5M CE": "35.59", "RSI 10M CE": "30.83", "RSI 15M CE": "32.81", "VWAP 5M CE": "683.75", "VWAP 10M CE": "682.91", "VWAP 15M CE": "685.83", "EMA 5M CE": "679.26", "EMA 10M CE": "720.84", "EMA 15M CE": "763.95", "ST 5M CE": "745.14", "ST 10M CE": "804.11", "ST 15M CE": "878.06", "Strike": "47100.0", "Last Update Time PE": "10:56:05", "Symbol PE": "NFO:BANKNIFTY2431347100PE", "LTP PE": "0.0", "RSI 5M PE": "46.6", "RSI 10M PE": "45.96", "RSI 15M PE": "45.08", "VWAP 5M PE": "124.44", "VWAP 10M PE": "124.01", "VWAP 15M PE": "125.02", "EMA 5M PE": "119.92", "EMA 10M PE": "120.2", "EMA 15M PE": "122.71", "ST 5M PE": "96.54", "ST 10M PE": "141.9", "ST 15M PE": "155.26"}, {"Last Update Time CE": "10:56:06", "Symbol CE": "NFO:BANKNIFTY2431347200CE", "LTP CE": "0.0", "RSI 5M CE": "34.58", "RSI 10M CE": "30.89", "RSI 15M CE": "32.1", "VWAP 5M CE": "605.87", "VWAP 10M CE": "606.06", "VWAP 15M CE": "610.75", "EMA 5M CE": "603.92", "EMA 10M CE": "644.55", "EMA 15M CE": "687.9", "ST 5M CE": "670.79", "ST 10M CE": "727.52", "ST 15M CE": "804.86", "Strike": "47200.0", "Last Update Time PE": "10:56:07", "Symbol PE": "NFO:BANKNIFTY2431347200PE", "LTP PE": "0.0", "RSI 5M PE": "47.47", "RSI 10M PE": "47.39", "RSI 15M PE": "46.66", "VWAP 5M PE": "149.32", "VWAP 10M PE": "148.81", "VWAP 15M PE": "149.71", "EMA 5M PE": "145.02", "EMA 10M PE": "144.43", "EMA 15M PE": "146.36", "ST 5M PE": "117.0", "ST 10M PE": "98.08", "ST 15M PE": "182.44"}, {"Last Update Time CE": "10:56:08", "Symbol CE": "NFO:BANKNIFTY2431347300CE", "LTP CE": "0.0", "RSI 5M CE": "35.12", "RSI 10M CE": "30.73", "RSI 15M CE": "31.89", "VWAP 5M CE": "537.55", "VWAP 10M CE": "537.51", "VWAP 15M CE": "541.05", "EMA 5M CE": "533.97", "EMA 10M CE": "573.36", "EMA 15M CE": "615.05", "ST 5M CE": "597.84", "ST 10M CE": "653.23", "ST 15M CE": "729.75", "Strike": "47300.0", "Last Update Time PE": "10:56:09", "Symbol PE": "NFO:BANKNIFTY2431347300PE", "LTP PE": "0.0", "RSI 5M PE": "48.47", "RSI 10M PE": "48.82", "RSI 15M PE": "48.14", "VWAP 5M PE": "179.73", "VWAP 10M PE": "179.15", "VWAP 15M PE": "180.1", "EMA 5M PE": "174.71", "EMA 10M PE": "172.94", "EMA 15M PE": "174.02", "ST 5M PE": "142.2", "ST 10M PE": "120.44", "ST 15M PE": "209.98"}, {"Last Update Time CE": "10:56:10", "Symbol CE": "NFO:BANKNIFTY2431347400CE", "LTP CE": "0.0", "RSI 5M CE": "34.11", "RSI 10M CE": "30.03", "RSI 15M CE": "31.78", "VWAP 5M CE": "473.96", "VWAP 10M CE": "473.29", "VWAP 15M CE": "478.28", "EMA 5M CE": "468.19", "EMA 10M CE": "506.22", "EMA 15M CE": "547.14", "ST 5M CE": "528.68", "ST 10M CE": "580.97", "ST 15M CE": "656.15", "Strike": "47400.0", "Last Update Time PE": "10:56:11", "Symbol PE": "NFO:BANKNIFTY2431347400PE", "LTP PE": "0.0", "RSI 5M PE": "49.7", "RSI 10M PE": "50.51", "RSI 15M PE": "49.61", "VWAP 5M PE": "213.27", "VWAP 10M PE": "212.66", "VWAP 15M PE": "213.58", "EMA 5M PE": "209.13", "EMA 10M PE": "205.84", "EMA 15M PE": "205.72", "ST 5M PE": "172.42", "ST 10M PE": "148.55", "ST 15M PE": "242.96"}, {"Last Update Time CE": "10:56:12", "Symbol CE": "NFO:BANKNIFTY2431347500CE", "LTP CE": "0.0", "RSI 5M CE": "33.98", "RSI 10M CE": "29.69", "RSI 15M CE": "31.17", "VWAP 5M CE": "410.2", "VWAP 10M CE": "410.17", "VWAP 15M CE": "415.05", "EMA 5M CE": "407.25", "EMA 10M CE": "443.73", "EMA 15M CE": "483.44", "ST 5M CE": "465.11", "ST 10M CE": "518.81", "ST 15M CE": "594.98", "Strike": "47500.0", "Last Update Time PE": "10:56:13", "Symbol PE": "NFO:BANKNIFTY2431347500PE", "LTP PE": "0.0", "RSI 5M PE": "50.56", "RSI 10M PE": "51.81", "RSI 15M PE": "51.14", "VWAP 5M PE": "253.59", "VWAP 10M PE": "253.15", "VWAP 15M PE": "254.1", "EMA 5M PE": "248.34", "EMA 10M PE": "243.47", "EMA 15M PE": "241.66", "ST 5M PE": "205.8", "ST 10M PE": "178.73", "ST 15M PE": "279.59"}, {"Last Update Time CE": "10:56:14", "Symbol CE": "NFO:BANKNIFTY2431347600CE", "LTP CE": "0.0", "RSI 5M CE": "33.32", "RSI 10M CE": "28.96", "RSI 15M CE": "30.82", "VWAP 5M CE": "351.89", "VWAP 10M CE": "351.45", "VWAP 15M CE": "355.13", "EMA 5M CE": "351.54", "EMA 10M CE": "386.3", "EMA 15M CE": "424.22", "ST 5M CE": "402.95", "ST 10M CE": "452.41", "ST 15M CE": "523.8", "Strike": "47600.0", "Last Update Time PE": "10:56:15", "Symbol PE": "NFO:BANKNIFTY2431347600PE", "LTP PE": "0.0", "RSI 5M PE": "51.37", "RSI 10M PE": "52.93", "RSI 15M PE": "52.4", "VWAP 5M PE": "297.6", "VWAP 10M PE": "296.68", "VWAP 15M PE": "297.45", "EMA 5M PE": "292.47", "EMA 10M PE": "285.78", "EMA 15M PE": "282.37", "ST 5M PE": "244.15", "ST 10M PE": "213.76", "ST 15M PE": "190.34"}, {"Last Update Time CE": "10:56:16", "Symbol CE": "NFO:BANKNIFTY2431347700CE", "LTP CE": "0.0", "RSI 5M CE": "32.64", "RSI 10M CE": "28.39", "RSI 15M CE": "30.45", "VWAP 5M CE": "308.25", "VWAP 10M CE": "307.62", "VWAP 15M CE": "311.25", "EMA 5M CE": "300.17", "EMA 10M CE": "333.0", "EMA 15M CE": "369.11", "ST 5M CE": "346.36", "ST 10M CE": "391.94", "ST 15M CE": "458.13", "Strike": "47700.0", "Last Update Time PE": "10:56:17", "Symbol PE": "NFO:BANKNIFTY2431347700PE", "LTP PE": "0.0", "RSI 5M PE": "52.12", "RSI 10M PE": "54.0", "RSI 15M PE": "53.47", "VWAP 5M PE": "344.99", "VWAP 10M PE": "344.32", "VWAP 15M PE": "344.63", "EMA 5M PE": "341.23", "EMA 10M PE": "332.47", "EMA 15M PE": "327.2", "ST 5M PE": "286.77", "ST 10M PE": "252.41", "ST 15M PE": "235.01"}, {"Last Update Time CE": "10:56:18", "Symbol CE": "NFO:BANKNIFTY2431347800CE", "LTP CE": "0.0", "RSI 5M CE": "32.14", "RSI 10M CE": "27.61", "RSI 15M CE": "30.27", "VWAP 5M CE": "265.81", "VWAP 10M CE": "265.07", "VWAP 15M CE": "269.04", "EMA 5M CE": "254.18", "EMA 10M CE": "284.94", "EMA 15M CE": "318.88", "ST 5M CE": "294.17", "ST 10M CE": "335.49", "ST 15M CE": "397.7", "Strike": "47800.0", "Last Update Time PE": "10:56:19", "Symbol PE": "NFO:BANKNIFTY2431347800PE", "LTP PE": "0.0", "RSI 5M PE": "53.28", "RSI 10M PE": "55.37", "RSI 15M PE": "54.68", "VWAP 5M PE": "398.3", "VWAP 10M PE": "397.61", "VWAP 15M PE": "397.24", "EMA 5M PE": "395.96", "EMA 10M PE": "385.16", "EMA 15M PE": "377.46", "ST 5M PE": "335.41", "ST 10M PE": "297.86", "ST 15M PE": "269.07"}, {"Last Update Time CE": "10:56:20", "Symbol CE": "NFO:BANKNIFTY2431347900CE", "LTP CE": "0.0", "RSI 5M CE": "31.54", "RSI 10M CE": "27.6", "RSI 15M CE": "29.98", "VWAP 5M CE": "222.28", "VWAP 10M CE": "221.73", "VWAP 15M CE": "224.81", "EMA 5M CE": "213.5", "EMA 10M CE": "241.85", "EMA 15M CE": "273.41", "ST 5M CE": "248.42", "ST 10M CE": "286.32", "ST 15M CE": "344.21", "Strike": "47900.0", "Last Update Time PE": "10:56:21", "Symbol PE": "NFO:BANKNIFTY2431347900PE", "LTP PE": "0.0", "RSI 5M PE": "53.81", "RSI 10M PE": "56.28", "RSI 15M PE": "55.65", "VWAP 5M PE": "456.05", "VWAP 10M PE": "455.34", "VWAP 15M PE": "454.52", "EMA 5M PE": "455.12", "EMA 10M PE": "441.98", "EMA 15M PE": "432.23", "ST 5M PE": "387.38", "ST 10M PE": "346.19", "ST 15M PE": "315.06"}, {"Last Update Time CE": "10:56:22", "Symbol CE": "NFO:BANKNIFTY2431348000CE", "LTP CE": "0.0", "RSI 5M CE": "31.27", "RSI 10M CE": "26.9", "RSI 15M CE": "29.77", "VWAP 5M CE": "186.56", "VWAP 10M CE": "186.14", "VWAP 15M CE": "189.41", "EMA 5M CE": "177.53", "EMA 10M CE": "203.45", "EMA 15M CE": "232.68", "ST 5M CE": "207.5", "ST 10M CE": "242.04", "ST 15M CE": "294.79", "Strike": "48000.0", "Last Update Time PE": "10:56:23", "Symbol PE": "NFO:BANKNIFTY2431348000PE", "LTP PE": "0.0", "RSI 5M PE": "54.91", "RSI 10M PE": "57.37", "RSI 15M PE": "56.71", "VWAP 5M PE": "519.1", "VWAP 10M PE": "518.58", "VWAP 15M PE": "517.91", "EMA 5M PE": "519.24", "EMA 10M PE": "503.51", "EMA 15M PE": "490.98", "ST 5M PE": "447.1", "ST 10M PE": "400.77", "ST 15M PE": "367.26"}, {"Last Update Time CE": "10:56:24", "Symbol CE": "NFO:BANKNIFTY2431348100CE", "LTP CE": "0.0", "RSI 5M CE": "30.8", "RSI 10M CE": "26.56", "RSI 15M CE": "29.54", "VWAP 5M CE": "153.75", "VWAP 10M CE": "153.41", "VWAP 15M CE": "156.02", "EMA 5M CE": "146.5", "EMA 10M CE": "170.12", "EMA 15M CE": "196.93", "ST 5M CE": "172.32", "ST 10M CE": "203.49", "ST 15M CE": "250.58", "Strike": "48100.0", "Last Update Time PE": "10:56:25", "Symbol PE": "NFO:BANKNIFTY2431348100PE", "LTP PE": "0.0", "RSI 5M PE": "55.44", "RSI 10M PE": "58.32", "RSI 15M PE": "57.41", "VWAP 5M PE": "585.84", "VWAP 10M PE": "585.15", "VWAP 15M PE": "583.81", "EMA 5M PE": "588.65", "EMA 10M PE": "570.59", "EMA 15M PE": "555.65", "ST 5M PE": "508.17", "ST 10M PE": "458.83", "ST 15M PE": "422.38"}, {"Last Update Time CE": "10:56:26", "Symbol CE": "NFO:BANKNIFTY2431348200CE", "LTP CE": "0.0", "RSI 5M CE": "30.54", "RSI 10M CE": "26.07", "RSI 15M CE": "29.35", "VWAP 5M CE": "127.82", "VWAP 10M CE": "127.42", "VWAP 15M CE": "130.08", "EMA 5M CE": "119.81", "EMA 10M CE": "141.03", "EMA 15M CE": "165.29", "ST 5M CE": "142.02", "ST 10M CE": "169.66", "ST 15M CE": "211.66", "Strike": "48200.0", "Last Update Time PE": "10:56:27", "Symbol PE": "NFO:BANKNIFTY2431348200PE", "LTP PE": "0.0", "RSI 5M PE": "55.84", "RSI 10M PE": "58.76", "RSI 15M PE": "58.26", "VWAP 5M PE": "662.23", "VWAP 10M PE": "661.68", "VWAP 15M PE": "660.89", "EMA 5M PE": "661.67", "EMA 10M PE": "640.94", "EMA 15M PE": "623.33", "ST 5M PE": "577.12", "ST 10M PE": "526.73", "ST 15M PE": "488.52"}]