[{"Last Update Time CE": "10:57:02", "Symbol CE": "NFO:BANKNIFTY24FEB46000CE", "LTP CE": "0.0", "RSI 5M CE": "41.78", "RSI 10M CE": "37.56", "RSI 15M CE": "38.33", "VWAP 5M CE": "910.57", "VWAP 10M CE": "916.54", "VWAP 15M CE": "909.02", "EMA 5M CE": "891.11", "EMA 10M CE": "932.09", "EMA 15M CE": "976.58", "ST 5M CE": "1042.79", "ST 10M CE": "1120.8", "ST 15M CE": "1208.86", "Strike": "46000.0", "Last Update Time PE": "10:57:03", "Symbol PE": "NFO:BANKNIFTY24FEB46000PE", "LTP PE": "0.0", "RSI 5M PE": "53.93", "RSI 10M PE": "56.36", "RSI 15M PE": "55.2", "VWAP 5M PE": "164.41", "VWAP 10M PE": "162.9", "VWAP 15M PE": "164.71", "EMA 5M PE": "165.94", "EMA 10M PE": "158.68", "EMA 15M PE": "153.06", "ST 5M PE": "125.82", "ST 10M PE": "92.59", "ST 15M PE": "70.11"}, {"Last Update Time CE": "10:57:04", "Symbol CE": "NFO:BANKNIFTY24FEB46100CE", "LTP CE": "0.0", "RSI 5M CE": "41.64", "RSI 10M CE": "37.43", "RSI 15M CE": "38.83", "VWAP 5M CE": "834.24", "VWAP 10M CE": "839.01", "VWAP 15M CE": "838.78", "EMA 5M CE": "815.29", "EMA 10M CE": "855.24", "EMA 15M CE": "898.43", "ST 5M CE": "951.49", "ST 10M CE": "1025.32", "ST 15M CE": "1108.73", "Strike": "46100.0", "Last Update Time PE": "10:57:05", "Symbol PE": "NFO:BANKNIFTY24FEB46100PE", "LTP PE": "0.0", "RSI 5M PE": "54.13", "RSI 10M PE": "56.74", "RSI 15M PE": "55.77", "VWAP 5M PE": "191.98", "VWAP 10M PE": "190.19", "VWAP 15M PE": "192.49", "EMA 5M PE": "191.1", "EMA 10M PE": "182.5", "EMA 15M PE": "175.63", "ST 5M PE": "146.25", "ST 10M PE": "108.11", "ST 15M PE": "84.75"}, {"Last Update Time CE": "10:57:06", "Symbol CE": "NFO:BANKNIFTY24FEB46200CE", "LTP CE": "0.0", "RSI 5M CE": "41.57", "RSI 10M CE": "37.36", "RSI 15M CE": "38.27", "VWAP 5M CE": "751.63", "VWAP 10M CE": "756.16", "VWAP 15M CE": "754.75", "EMA 5M CE": "744.87", "EMA 10M CE": "783.46", "EMA 15M CE": "825.41", "ST 5M CE": "878.16", "ST 10M CE": "949.18", "ST 15M CE": "1029.88", "Strike": "46200.0", "Last Update Time PE": "10:57:07", "Symbol PE": "NFO:BANKNIFTY24FEB46200PE", "LTP PE": "0.0", "RSI 5M PE": "54.48", "RSI 10M PE": "57.29", "RSI 15M PE": "55.99", "VWAP 5M PE": "218.38", "VWAP 10M PE": "216.38", "VWAP 15M PE": "218.63", "EMA 5M PE": "219.17", "EMA 10M PE": "209.18", "EMA 15M PE": "200.95", "ST 5M PE": "169.29", "ST 10M PE": "127.15", "ST 15M PE": "102.27"}, {"Last Update Time CE": "10:57:08", "Symbol CE": "NFO:BANKNIFTY24FEB46300CE", "LTP CE": "0.0", "RSI 5M CE": "41.36", "RSI 10M CE": "37.22", "RSI 15M CE": "37.94", "VWAP 5M CE": "683.57", "VWAP 10M CE": "689.6", "VWAP 15M CE": "687.71", "EMA 5M CE": "675.45", "EMA 10M CE": "712.48", "EMA 15M CE": "752.75", "ST 5M CE": "806.74", "ST 10M CE": "876.47", "ST 15M CE": "959.87", "Strike": "46300.0", "Last Update Time PE": "10:57:09", "Symbol PE": "NFO:BANKNIFTY24FEB46300PE", "LTP PE": "0.0", "RSI 5M PE": "54.7", "RSI 10M PE": "57.59", "RSI 15M PE": "56.14", "VWAP 5M PE": "250.08", "VWAP 10M PE": "248.26", "VWAP 15M PE": "250.92", "EMA 5M PE": "250.14", "EMA 10M PE": "238.88", "EMA 15M PE": "229.51", "ST 5M PE": "195.47", "ST 10M PE": "148.29", "ST 15M PE": "120.24"}, {"Last Update Time CE": "10:57:10", "Symbol CE": "NFO:BANKNIFTY24FEB46400CE", "LTP CE": "0.0", "RSI 5M CE": "41.31", "RSI 10M CE": "37.21", "RSI 15M CE": "38.01", "VWAP 5M CE": "625.42", "VWAP 10M CE": "628.47", "VWAP 15M CE": "626.31", "EMA 5M CE": "610.46", "EMA 10M CE": "646.08", "EMA 15M CE": "684.43", "ST 5M CE": "733.47", "ST 10M CE": "802.63", "ST 15M CE": "885.4", "Strike": "46400.0", "Last Update Time PE": "10:57:11", "Symbol PE": "NFO:BANKNIFTY24FEB46400PE", "LTP PE": "0.0", "RSI 5M PE": "54.67", "RSI 10M PE": "57.77", "RSI 15M PE": "56.65", "VWAP 5M PE": "286.95", "VWAP 10M PE": "284.36", "VWAP 15M PE": "287.12", "EMA 5M PE": "284.67", "EMA 10M PE": "271.48", "EMA 15M PE": "260.59", "ST 5M PE": "224.06", "ST 10M PE": "171.72", "ST 15M PE": "142.67"}, {"Last Update Time CE": "10:57:12", "Symbol CE": "NFO:BANKNIFTY24FEB46500CE", "LTP CE": "0.0", "RSI 5M CE": "41.33", "RSI 10M CE": "37.26", "RSI 15M CE": "37.99", "VWAP 5M CE": "559.97", "VWAP 10M CE": "560.94", "VWAP 15M CE": "558.26", "EMA 5M CE": "548.55", "EMA 10M CE": "582.21", "EMA 15M CE": "619.04", "ST 5M CE": "667.14", "ST 10M CE": "740.77", "ST 15M CE": "829.59", "Strike": "46500.0", "Last Update Time PE": "10:57:13", "Symbol PE": "NFO:BANKNIFTY24FEB46500PE", "LTP PE": "0.0", "RSI 5M PE": "54.84", "RSI 10M PE": "58.12", "RSI 15M PE": "56.88", "VWAP 5M PE": "322.18", "VWAP 10M PE": "319.32", "VWAP 15M PE": "322.49", "EMA 5M PE": "322.44", "EMA 10M PE": "307.88", "EMA 15M PE": "295.24", "ST 5M PE": "255.47", "ST 10M PE": "198.17", "ST 15M PE": "167.04"}, {"Last Update Time CE": "10:57:14", "Symbol CE": "NFO:BANKNIFTY24FEB46600CE", "LTP CE": "0.0", "RSI 5M CE": "40.98", "RSI 10M CE": "37.17", "RSI 15M CE": "37.83", "VWAP 5M CE": "499.16", "VWAP 10M CE": "500.82", "VWAP 15M CE": "499.43", "EMA 5M CE": "489.52", "EMA 10M CE": "521.77", "EMA 15M CE": "556.9", "ST 5M CE": "600.51", "ST 10M CE": "667.31", "ST 15M CE": "749.26", "Strike": "46600.0", "Last Update Time PE": "10:57:15", "Symbol PE": "NFO:BANKNIFTY24FEB46600PE", "LTP PE": "0.0", "RSI 5M PE": "55.09", "RSI 10M PE": "58.44", "RSI 15M PE": "57.13", "VWAP 5M PE": "364.84", "VWAP 10M PE": "362.49", "VWAP 15M PE": "365.62", "EMA 5M PE": "364.48", "EMA 10M PE": "348.33", "EMA 15M PE": "333.94", "ST 5M PE": "291.41", "ST 10M PE": "229.44", "ST 15M PE": "194.41"}, {"Last Update Time CE": "10:57:16", "Symbol CE": "NFO:BANKNIFTY24FEB46700CE", "LTP CE": "0.0", "RSI 5M CE": "40.97", "RSI 10M CE": "37.18", "RSI 15M CE": "37.7", "VWAP 5M CE": "451.64", "VWAP 10M CE": "452.92", "VWAP 15M CE": "451.71", "EMA 5M CE": "434.9", "EMA 10M CE": "465.53", "EMA 15M CE": "498.97", "ST 5M CE": "537.13", "ST 10M CE": "600.16", "ST 15M CE": "678.39", "Strike": "46700.0", "Last Update Time PE": "10:57:17", "Symbol PE": "NFO:BANKNIFTY24FEB46700PE", "LTP PE": "0.0", "RSI 5M PE": "55.21", "RSI 10M PE": "58.58", "RSI 15M PE": "57.4", "VWAP 5M PE": "407.39", "VWAP 10M PE": "404.01", "VWAP 15M PE": "407.63", "EMA 5M PE": "409.69", "EMA 10M PE": "391.94", "EMA 15M PE": "375.81", "ST 5M PE": "330.56", "ST 10M PE": "263.66", "ST 15M PE": "225.73"}, {"Last Update Time CE": "10:57:18", "Symbol CE": "NFO:BANKNIFTY24FEB46800CE", "LTP CE": "0.0", "RSI 5M CE": "40.85", "RSI 10M CE": "37.04", "RSI 15M CE": "37.39", "VWAP 5M CE": "411.0", "VWAP 10M CE": "412.08", "VWAP 15M CE": "409.28", "EMA 5M CE": "384.05", "EMA 10M CE": "412.85", "EMA 15M CE": "444.99", "ST 5M CE": "477.79", "ST 10M CE": "535.99", "ST 15M CE": "609.77", "Strike": "46800.0", "Last Update Time PE": "10:57:19", "Symbol PE": "NFO:BANKNIFTY24FEB46800PE", "LTP PE": "0.0", "RSI 5M PE": "55.34", "RSI 10M PE": "58.78", "RSI 15M PE": "57.47", "VWAP 5M PE": "446.93", "VWAP 10M PE": "444.18", "VWAP 15M PE": "451.56", "EMA 5M PE": "458.91", "EMA 10M PE": "439.36", "EMA 15M PE": "421.54", "ST 5M PE": "373.0", "ST 10M PE": "302.88", "ST 15M PE": "261.82"}, {"Last Update Time CE": "10:57:20", "Symbol CE": "NFO:BANKNIFTY24FEB46900CE", "LTP CE": "0.0", "RSI 5M CE": "40.64", "RSI 10M CE": "36.89", "RSI 15M CE": "37.48", "VWAP 5M CE": "364.77", "VWAP 10M CE": "364.62", "VWAP 15M CE": "361.32", "EMA 5M CE": "337.82", "EMA 10M CE": "364.56", "EMA 15M CE": "394.44", "ST 5M CE": "424.5", "ST 10M CE": "479.57", "ST 15M CE": "551.82", "Strike": "46900.0", "Last Update Time PE": "10:57:21", "Symbol PE": "NFO:BANKNIFTY24FEB46900PE", "LTP PE": "0.0", "RSI 5M PE": "55.52", "RSI 10M PE": "59.23", "RSI 15M PE": "57.96", "VWAP 5M PE": "493.64", "VWAP 10M PE": "492.2", "VWAP 15M PE": "502.63", "EMA 5M PE": "511.88", "EMA 10M PE": "490.23", "EMA 15M PE": "470.26", "ST 5M PE": "418.05", "ST 10M PE": "343.29", "ST 15M PE": "299.62"}, {"Last Update Time CE": "10:57:22", "Symbol CE": "NFO:BANKNIFTY24FEB47000CE", "LTP CE": "0.0", "RSI 5M CE": "40.54", "RSI 10M CE": "36.83", "RSI 15M CE": "37.31", "VWAP 5M CE": "315.54", "VWAP 10M CE": "316.95", "VWAP 15M CE": "315.17", "EMA 5M CE": "295.18", "EMA 10M CE": "319.92", "EMA 15M CE": "347.85", "ST 5M CE": "372.23", "ST 10M CE": "422.64", "ST 15M CE": "488.24", "Strike": "47000.0", "Last Update Time PE": "10:57:23", "Symbol PE": "NFO:BANKNIFTY24FEB47000PE", "LTP PE": "0.0", "RSI 5M PE": "55.62", "RSI 10M PE": "59.46", "RSI 15M PE": "58.3", "VWAP 5M PE": "555.85", "VWAP 10M PE": "552.65", "VWAP 15M PE": "560.16", "EMA 5M PE": "568.35", "EMA 10M PE": "544.44", "EMA 15M PE": "522.7", "ST 5M PE": "465.73", "ST 10M PE": "387.96", "ST 15M PE": "341.28"}, {"Last Update Time CE": "10:57:24", "Symbol CE": "NFO:BANKNIFTY24FEB47100CE", "LTP CE": "0.0", "RSI 5M CE": "40.4", "RSI 10M CE": "36.42", "RSI 15M CE": "36.95", "VWAP 5M CE": "279.99", "VWAP 10M CE": "280.18", "VWAP 15M CE": "277.44", "EMA 5M CE": "256.97", "EMA 10M CE": "279.92", "EMA 15M CE": "305.86", "ST 5M CE": "327.0", "ST 10M CE": "374.62", "ST 15M CE": "435.39", "Strike": "47100.0", "Last Update Time PE": "10:57:25", "Symbol PE": "NFO:BANKNIFTY24FEB47100PE", "LTP PE": "0.0", "RSI 5M PE": "55.94", "RSI 10M PE": "59.65", "RSI 15M PE": "58.1", "VWAP 5M PE": "612.68", "VWAP 10M PE": "610.25", "VWAP 15M PE": "618.2", "EMA 5M PE": "630.27", "EMA 10M PE": "604.66", "EMA 15M PE": "580.47", "ST 5M PE": "518.98", "ST 10M PE": "437.14", "ST 15M PE": "387.64"}, {"Last Update Time CE": "10:57:26", "Symbol CE": "NFO:BANKNIFTY24FEB47200CE", "LTP CE": "0.0", "RSI 5M CE": "40.29", "RSI 10M CE": "36.76", "RSI 15M CE": "36.99", "VWAP 5M CE": "238.17", "VWAP 10M CE": "239.21", "VWAP 15M CE": "238.7", "EMA 5M CE": "221.9", "EMA 10M CE": "242.95", "EMA 15M CE": "266.95", "ST 5M CE": "284.07", "ST 10M CE": "327.45", "ST 15M CE": "382.71", "Strike": "47200.0", "Last Update Time PE": "10:57:27", "Symbol PE": "NFO:BANKNIFTY24FEB47200PE", "LTP PE": "0.0", "RSI 5M PE": "56.02", "RSI 10M PE": "60.04", "RSI 15M PE": "58.46", "VWAP 5M PE": "669.86", "VWAP 10M PE": "669.69", "VWAP 15M PE": "678.86", "EMA 5M PE": "695.58", "EMA 10M PE": "667.94", "EMA 15M PE": "641.81", "ST 5M PE": "580.05", "ST 10M PE": "490.03", "ST 15M PE": "435.98"}]