[{"Last Update Time CE": "09:27:49", "Symbol CE": "NFO:BANKNIFTY2381044400CE", "LTP CE": "560.0", "RSI 5M CE": "49.81", "RSI 10M CE": "50.37", "RSI 15M CE": "48.91", "VWAP 5M CE": "586.24", "VWAP 10M CE": "579.03", "VWAP 15M CE": "503.96", "EMA 5M CE": "560.92", "EMA 10M CE": "551.55", "EMA 15M CE": "558.58", "ST 5M CE": "612.88", "ST 10M CE": "686.87", "ST 15M CE": "700.37", "Strike": "44400.0", "Last Update Time PE": "09:27:59", "Symbol PE": "NFO:BANKNIFTY2381044400PE", "LTP PE": "98.15", "RSI 5M PE": "42.5", "RSI 10M PE": "40.68", "RSI 15M PE": "42.24", "VWAP 5M PE": "89.58", "VWAP 10M PE": "92.07", "VWAP 15M PE": "151.46", "EMA 5M PE": "109.57", "EMA 10M PE": "120.88", "EMA 15M PE": "128.09", "ST 5M PE": "153.44", "ST 10M PE": "76.13", "ST 15M PE": "187.1"}, {"Last Update Time CE": "09:28:09", "Symbol CE": "NFO:BANKNIFTY2381044500CE", "LTP CE": "485.6", "RSI 5M CE": "49.29", "RSI 10M CE": "49.82", "RSI 15M CE": "49.05", "VWAP 5M CE": "506.75", "VWAP 10M CE": "498.27", "VWAP 15M CE": "442.21", "EMA 5M CE": "486.3", "EMA 10M CE": "478.68", "EMA 15M CE": "486.37", "ST 5M CE": "538.14", "ST 10M CE": "607.22", "ST 15M CE": "619.61", "Strike": "44500.0", "Last Update Time PE": "09:28:20", "Symbol PE": "NFO:BANKNIFTY2381044500PE", "LTP PE": "116.1", "RSI 5M PE": "42.87", "RSI 10M PE": "41.03", "RSI 15M PE": "41.96", "VWAP 5M PE": "111.77", "VWAP 10M PE": "115.27", "VWAP 15M PE": "182.55", "EMA 5M PE": "134.49", "EMA 10M PE": "147.24", "EMA 15M PE": "155.06", "ST 5M PE": "186.5", "ST 10M PE": "92.89", "ST 15M PE": "219.53"}, {"Last Update Time CE": "09:28:29", "Symbol CE": "NFO:BANKNIFTY2381044600CE", "LTP CE": "430.75", "RSI 5M CE": "48.97", "RSI 10M CE": "49.4", "RSI 15M CE": "48.52", "VWAP 5M CE": "434.65", "VWAP 10M CE": "428.25", "VWAP 15M CE": "373.91", "EMA 5M CE": "417.19", "EMA 10M CE": "410.96", "EMA 15M CE": "418.79", "ST 5M CE": "467.52", "ST 10M CE": "531.75", "ST 15M CE": "543.98", "Strike": "44600.0", "Last Update Time PE": "09:28:39", "Symbol PE": "NFO:BANKNIFTY2381044600PE", "LTP PE": "142.5", "RSI 5M PE": "43.4", "RSI 10M PE": "41.64", "RSI 15M PE": "42.71", "VWAP 5M PE": "140.59", "VWAP 10M PE": "144.17", "VWAP 15M PE": "225.26", "EMA 5M PE": "164.8", "EMA 10M PE": "179.12", "EMA 15M PE": "187.19", "ST 5M PE": "228.93", "ST 10M PE": "115.66", "ST 15M PE": "102.65"}, {"Last Update Time CE": "09:28:49", "Symbol CE": "NFO:BANKNIFTY2381044700CE", "LTP CE": "359.55", "RSI 5M CE": "48.67", "RSI 10M CE": "48.98", "RSI 15M CE": "47.51", "VWAP 5M CE": "368.28", "VWAP 10M CE": "364.32", "VWAP 15M CE": "326.37", "EMA 5M CE": "352.47", "EMA 10M CE": "347.72", "EMA 15M CE": "355.84", "ST 5M CE": "400.78", "ST 10M CE": "460.5", "ST 15M CE": "472.67", "Strike": "44700.0", "Last Update Time PE": "09:29:00", "Symbol PE": "NFO:BANKNIFTY2381044700PE", "LTP PE": "174.0", "RSI 5M PE": "44.1", "RSI 10M PE": "42.23", "RSI 15M PE": "43.19", "VWAP 5M PE": "175.17", "VWAP 10M PE": "180.82", "VWAP 15M PE": "257.25", "EMA 5M PE": "200.77", "EMA 10M PE": "216.55", "EMA 15M PE": "224.99", "ST 5M PE": "278.95", "ST 10M PE": "141.93", "ST 15M PE": "130.93"}, {"Last Update Time CE": "09:29:09", "Symbol CE": "NFO:BANKNIFTY2381044800CE", "LTP CE": "294.0", "RSI 5M CE": "48.07", "RSI 10M CE": "48.3", "RSI 15M CE": "47.24", "VWAP 5M CE": "316.28", "VWAP 10M CE": "320.88", "VWAP 15M CE": "291.84", "EMA 5M CE": "295.16", "EMA 10M CE": "291.84", "EMA 15M CE": "300.08", "ST 5M CE": "341.07", "ST 10M CE": "394.83", "ST 15M CE": "405.83", "Strike": "44800.0", "Last Update Time PE": "09:29:19", "Symbol PE": "NFO:BANKNIFTY2381044800PE", "LTP PE": "220.4", "RSI 5M PE": "44.35", "RSI 10M PE": "42.65", "RSI 15M PE": "43.45", "VWAP 5M PE": "209.9", "VWAP 10M PE": "213.9", "VWAP 15M PE": "282.22", "EMA 5M PE": "242.35", "EMA 10M PE": "259.55", "EMA 15M PE": "268.0", "ST 5M PE": "318.57", "ST 10M PE": "176.33", "ST 15M PE": "164.96"}, {"Last Update Time CE": "09:29:29", "Symbol CE": "NFO:BANKNIFTY2381044900CE", "LTP CE": "244.65", "RSI 5M CE": "47.53", "RSI 10M CE": "47.69", "RSI 15M CE": "46.31", "VWAP 5M CE": "250.1", "VWAP 10M CE": "245.27", "VWAP 15M CE": "259.36", "EMA 5M CE": "242.98", "EMA 10M CE": "240.9", "EMA 15M CE": "249.47", "ST 5M CE": "285.74", "ST 10M CE": "335.16", "ST 15M CE": "345.73", "Strike": "44900.0", "Last Update Time PE": "09:29:39", "Symbol PE": "NFO:BANKNIFTY2381044900PE", "LTP PE": "255.65", "RSI 5M PE": "44.88", "RSI 10M PE": "43.13", "RSI 15M PE": "44.2", "VWAP 5M PE": "256.8", "VWAP 10M PE": "259.88", "VWAP 15M PE": "310.4", "EMA 5M PE": "290.79", "EMA 10M PE": "309.32", "EMA 15M PE": "318.01", "ST 5M PE": "383.39", "ST 10M PE": "216.14", "ST 15M PE": "203.2"}, {"Last Update Time CE": "09:29:49", "Symbol CE": "NFO:BANKNIFTY2381045000CE", "LTP CE": "194.05", "RSI 5M CE": "47.05", "RSI 10M CE": "47.11", "RSI 15M CE": "45.73", "VWAP 5M CE": "206.05", "VWAP 10M CE": "203.52", "VWAP 15M CE": "228.32", "EMA 5M CE": "198.6", "EMA 10M CE": "197.48", "EMA 15M CE": "205.39", "ST 5M CE": "237.96", "ST 10M CE": "281.96", "ST 15M CE": "291.58", "Strike": "45000.0", "Last Update Time PE": "09:30:00", "Symbol PE": "NFO:BANKNIFTY2381045000PE", "LTP PE": "317.95", "RSI 5M PE": "45.28", "RSI 10M PE": "43.69", "RSI 15M PE": "44.53", "VWAP 5M PE": "309.53", "VWAP 10M PE": "314.62", "VWAP 15M PE": "344.98", "EMA 5M PE": "345.67", "EMA 10M PE": "365.33", "EMA 15M PE": "373.4", "ST 5M PE": "442.32", "ST 10M PE": "263.23", "ST 15M PE": "250.67"}, {"Last Update Time CE": "09:30:09", "Symbol CE": "NFO:BANKNIFTY2381045100CE", "LTP CE": "143.75", "RSI 5M CE": "47.29", "RSI 10M CE": "46.41", "RSI 15M CE": "45.44", "VWAP 5M CE": "160.43", "VWAP 10M CE": "158.92", "VWAP 15M CE": "159.08", "EMA 5M CE": "158.92", "EMA 10M CE": "159.53", "EMA 15M CE": "165.4", "ST 5M CE": "196.08", "ST 10M CE": "234.83", "ST 15M CE": "243.66", "Strike": "45100.0", "Last Update Time PE": "09:30:19", "Symbol PE": "NFO:BANKNIFTY2381045100PE", "LTP PE": "393.9", "RSI 5M PE": "43.6", "RSI 10M PE": "43.97", "RSI 15M PE": "42.19", "VWAP 5M PE": "373.52", "VWAP 10M PE": "373.35", "VWAP 15M PE": "372.32", "EMA 5M PE": "402.91", "EMA 10M PE": "427.53", "EMA 15M PE": "427.48", "ST 5M PE": "512.97", "ST 10M PE": "317.6", "ST 15M PE": "305.51"}, {"Last Update Time CE": "09:30:29", "Symbol CE": "NFO:BANKNIFTY2381045200CE", "LTP CE": "113.35", "RSI 5M CE": "46.07", "RSI 10M CE": "45.51", "RSI 15M CE": "44.19", "VWAP 5M CE": "126.25", "VWAP 10M CE": "126.17", "VWAP 15M CE": "126.1", "EMA 5M CE": "126.94", "EMA 10M CE": "128.43", "EMA 15M CE": "133.49", "ST 5M CE": "159.85", "ST 10M CE": "193.34", "ST 15M CE": "201.2", "Strike": "45200.0", "Last Update Time PE": "09:30:39", "Symbol PE": "NFO:BANKNIFTY2381045200PE", "LTP PE": "472.5", "RSI 5M PE": "43.81", "RSI 10M PE": "44.38", "RSI 15M PE": "42.56", "VWAP 5M PE": "440.42", "VWAP 10M PE": "443.12", "VWAP 15M PE": "442.3", "EMA 5M PE": "470.35", "EMA 10M PE": "495.67", "EMA 15M PE": "494.63", "ST 5M PE": "589.41", "ST 10M PE": "376.5", "ST 15M PE": "363.1"}, {"Last Update Time CE": "09:30:49", "Symbol CE": "NFO:BANKNIFTY2381045300CE", "LTP CE": "84.9", "RSI 5M CE": "45.32", "RSI 10M CE": "44.76", "RSI 15M CE": "43.07", "VWAP 5M CE": "98.28", "VWAP 10M CE": "99.32", "VWAP 15M CE": "99.18", "EMA 5M CE": "99.72", "EMA 10M CE": "101.74", "EMA 15M CE": "106.17", "ST 5M CE": "129.54", "ST 10M CE": "157.53", "ST 15M CE": "164.73", "Strike": "45300.0", "Last Update Time PE": "09:30:59", "Symbol PE": "NFO:BANKNIFTY2381045300PE", "LTP PE": "556.5", "RSI 5M PE": "44.35", "RSI 10M PE": "44.9", "RSI 15M PE": "43.14", "VWAP 5M PE": "513.42", "VWAP 10M PE": "515.88", "VWAP 15M PE": "514.6", "EMA 5M PE": "544.0", "EMA 10M PE": "569.96", "EMA 15M PE": "568.68", "ST 5M PE": "675.95", "ST 10M PE": "443.56", "ST 15M PE": "428.28"}, {"Last Update Time CE": "09:31:09", "Symbol CE": "NFO:BANKNIFTY2381045400CE", "LTP CE": "63.65", "RSI 5M CE": "44.02", "RSI 10M CE": "43.84", "RSI 15M CE": "41.95", "VWAP 5M CE": "76.13", "VWAP 10M CE": "77.77", "VWAP 15M CE": "77.28", "EMA 5M CE": "78.32", "EMA 10M CE": "80.63", "EMA 15M CE": "84.34", "ST 5M CE": "104.21", "ST 10M CE": "127.81", "ST 15M CE": "133.81", "Strike": "45400.0", "Last Update Time PE": "09:31:19", "Symbol PE": "NFO:BANKNIFTY2381045400PE", "LTP PE": "642.5", "RSI 5M PE": "44.52", "RSI 10M PE": "45.16", "RSI 15M PE": "43.47", "VWAP 5M PE": "587.86", "VWAP 10M PE": "594.65", "VWAP 15M PE": "593.23", "EMA 5M PE": "622.23", "EMA 10M PE": "648.64", "EMA 15M PE": "646.5", "ST 5M PE": "758.42", "ST 10M PE": "517.78", "ST 15M PE": "501.69"}]