[{"Last Update Time CE": "11:44:29", "Symbol CE": "NFO:NIFTY2430722200CE", "LTP CE": "0.0", "RSI 5M CE": "56.13", "RSI 10M CE": "60.21", "RSI 15M CE": "61.53", "VWAP 5M CE": "289.17", "VWAP 10M CE": "290.29", "VWAP 15M CE": "287.0", "EMA 5M CE": "298.98", "EMA 10M CE": "292.18", "EMA 15M CE": "274.83", "ST 5M CE": "321.07", "ST 10M CE": "235.59", "ST 15M CE": "215.29", "Strike": "22200.0", "Last Update Time PE": "11:44:30", "Symbol PE": "NFO:NIFTY2430722200PE", "LTP PE": "0.0", "RSI 5M PE": "23.76", "RSI 10M PE": "27.0", "RSI 15M PE": "29.45", "VWAP 5M PE": "2.94", "VWAP 10M PE": "2.97", "VWAP 15M PE": "3.06", "EMA 5M PE": "1.89", "EMA 10M PE": "4.18", "EMA 15M PE": "8.14", "ST 5M PE": "2.91", "ST 10M PE": "7.39", "ST 15M PE": "14.46"}, {"Last Update Time CE": "11:44:31", "Symbol CE": "NFO:NIFTY2430722250CE", "LTP CE": "0.0", "RSI 5M CE": "55.41", "RSI 10M CE": "59.37", "RSI 15M CE": "61.08", "VWAP 5M CE": "239.71", "VWAP 10M CE": "241.0", "VWAP 15M CE": "237.24", "EMA 5M CE": "249.63", "EMA 10M CE": "243.8", "EMA 15M CE": "228.16", "ST 5M CE": "269.98", "ST 10M CE": "193.73", "ST 15M CE": "176.09", "Strike": "22250.0", "Last Update Time PE": "11:44:32", "Symbol PE": "NFO:NIFTY2430722250PE", "LTP PE": "0.0", "RSI 5M PE": "24.46", "RSI 10M PE": "26.79", "RSI 15M PE": "29.18", "VWAP 5M PE": "4.2", "VWAP 10M PE": "4.22", "VWAP 15M PE": "4.34", "EMA 5M PE": "2.6", "EMA 10M PE": "5.76", "EMA 15M PE": "11.19", "ST 5M PE": "4.19", "ST 10M PE": "10.33", "ST 15M PE": "19.55"}, {"Last Update Time CE": "11:44:33", "Symbol CE": "NFO:NIFTY2430722300CE", "LTP CE": "0.0", "RSI 5M CE": "54.92", "RSI 10M CE": "58.44", "RSI 15M CE": "60.08", "VWAP 5M CE": "191.63", "VWAP 10M CE": "192.46", "VWAP 15M CE": "188.93", "EMA 5M CE": "200.84", "EMA 10M CE": "196.19", "EMA 15M CE": "182.26", "ST 5M CE": "221.47", "ST 10M CE": "153.68", "ST 15M CE": "139.08", "Strike": "22300.0", "Last Update Time PE": "11:44:34", "Symbol PE": "NFO:NIFTY2430722300PE", "LTP PE": "0.0", "RSI 5M PE": "24.89", "RSI 10M PE": "26.51", "RSI 15M PE": "28.77", "VWAP 5M PE": "6.27", "VWAP 10M PE": "6.33", "VWAP 15M PE": "6.53", "EMA 5M PE": "3.77", "EMA 10M PE": "8.1", "EMA 15M PE": "15.38", "ST 5M PE": "6.19", "ST 10M PE": "14.39", "ST 15M PE": "25.98"}, {"Last Update Time CE": "11:44:35", "Symbol CE": "NFO:NIFTY2430722350CE", "LTP CE": "0.0", "RSI 5M CE": "54.39", "RSI 10M CE": "57.11", "RSI 15M CE": "58.67", "VWAP 5M CE": "143.57", "VWAP 10M CE": "144.92", "VWAP 15M CE": "141.38", "EMA 5M CE": "152.48", "EMA 10M CE": "149.38", "EMA 15M CE": "137.96", "ST 5M CE": "107.88", "ST 10M CE": "193.46", "ST 15M CE": "104.93", "Strike": "22350.0", "Last Update Time PE": "11:44:36", "Symbol PE": "NFO:NIFTY2430722350PE", "LTP PE": "0.0", "RSI 5M PE": "26.11", "RSI 10M PE": "26.33", "RSI 15M PE": "28.39", "VWAP 5M PE": "9.31", "VWAP 10M PE": "9.33", "VWAP 15M PE": "9.66", "EMA 5M PE": "5.74", "EMA 10M PE": "11.57", "EMA 15M PE": "21.19", "ST 5M PE": "9.62", "ST 10M PE": "20.63", "ST 15M PE": "35.13"}, {"Last Update Time CE": "11:44:37", "Symbol CE": "NFO:NIFTY2430722400CE", "LTP CE": "0.0", "RSI 5M CE": "53.28", "RSI 10M CE": "55.57", "RSI 15M CE": "56.75", "VWAP 5M CE": "100.23", "VWAP 10M CE": "101.58", "VWAP 15M CE": "97.89", "EMA 5M CE": "106.36", "EMA 10M CE": "105.25", "EMA 15M CE": "96.7", "ST 5M CE": "64.67", "ST 10M CE": "141.78", "ST 15M CE": "150.67", "Strike": "22400.0", "Last Update Time PE": "11:44:38", "Symbol PE": "NFO:NIFTY2430722400PE", "LTP PE": "0.0", "RSI 5M PE": "28.05", "RSI 10M PE": "27.1", "RSI 15M PE": "28.42", "VWAP 5M PE": "15.3", "VWAP 10M PE": "15.35", "VWAP 15M PE": "15.97", "EMA 5M PE": "9.6", "EMA 10M PE": "17.45", "EMA 15M PE": "29.96", "ST 5M PE": "16.19", "ST 10M PE": "31.2", "ST 15M PE": "49.07"}, {"Last Update Time CE": "11:44:39", "Symbol CE": "NFO:NIFTY2430722450CE", "LTP CE": "0.0", "RSI 5M CE": "51.19", "RSI 10M CE": "53.0", "RSI 15M CE": "53.7", "VWAP 5M CE": "60.82", "VWAP 10M CE": "62.11", "VWAP 15M CE": "58.92", "EMA 5M CE": "63.77", "EMA 10M CE": "65.14", "EMA 15M CE": "60.18", "ST 5M CE": "27.39", "ST 10M CE": "92.91", "ST 15M CE": "99.58", "Strike": "22450.0", "Last Update Time PE": "11:44:40", "Symbol PE": "NFO:NIFTY2430722450PE", "LTP PE": "0.0", "RSI 5M PE": "31.61", "RSI 10M PE": "28.83", "RSI 15M PE": "28.87", "VWAP 5M PE": "25.82", "VWAP 10M PE": "25.95", "VWAP 15M PE": "27.25", "EMA 5M PE": "17.09", "EMA 10M PE": "27.37", "EMA 15M PE": "43.39", "ST 5M PE": "28.55", "ST 10M PE": "48.54", "ST 15M PE": "70.51"}, {"Last Update Time CE": "11:44:41", "Symbol CE": "NFO:NIFTY2430722500CE", "LTP CE": "0.0", "RSI 5M CE": "47.73", "RSI 10M CE": "49.47", "RSI 15M CE": "49.29", "VWAP 5M CE": "34.0", "VWAP 10M CE": "34.85", "VWAP 15M CE": "33.3", "EMA 5M CE": "31.28", "EMA 10M CE": "34.54", "EMA 15M CE": "33.07", "ST 5M CE": "4.57", "ST 10M CE": "56.67", "ST 15M CE": "62.66", "Strike": "22500.0", "Last Update Time PE": "11:44:42", "Symbol PE": "NFO:NIFTY2430722500PE", "LTP PE": "0.0", "RSI 5M PE": "35.68", "RSI 10M PE": "31.56", "RSI 15M PE": "30.07", "VWAP 5M PE": "46.46", "VWAP 10M PE": "46.66", "VWAP 15M PE": "49.24", "EMA 5M PE": "34.46", "EMA 10M PE": "46.78", "EMA 15M PE": "66.28", "ST 5M PE": "55.39", "ST 10M PE": "81.43", "ST 15M PE": "108.54"}, {"Last Update Time CE": "11:44:43", "Symbol CE": "NFO:NIFTY2430722550CE", "LTP CE": "0.0", "RSI 5M CE": "45.82", "RSI 10M CE": "46.52", "RSI 15M CE": "46.29", "VWAP 5M CE": "17.11", "VWAP 10M CE": "17.59", "VWAP 15M CE": "16.91", "EMA 5M CE": "14.64", "EMA 10M CE": "17.57", "EMA 15M CE": "17.7", "ST 5M CE": "21.9", "ST 10M CE": "33.15", "ST 15M CE": "37.38", "Strike": "22550.0", "Last Update Time PE": "11:44:44", "Symbol PE": "NFO:NIFTY2430722550PE", "LTP PE": "0.0", "RSI 5M PE": "39.64", "RSI 10M PE": "34.44", "RSI 15M PE": "32.36", "VWAP 5M PE": "78.96", "VWAP 10M PE": "79.05", "VWAP 15M PE": "82.25", "EMA 5M PE": "67.76", "EMA 10M PE": "79.74", "EMA 15M PE": "100.78", "ST 5M PE": "101.01", "ST 10M PE": "131.02", "ST 15M PE": "160.78"}, {"Last Update Time CE": "11:44:45", "Symbol CE": "NFO:NIFTY2430722600CE", "LTP CE": "0.0", "RSI 5M CE": "44.42", "RSI 10M CE": "45.52", "RSI 15M CE": "44.91", "VWAP 5M CE": "9.37", "VWAP 10M CE": "9.64", "VWAP 15M CE": "9.24", "EMA 5M CE": "7.48", "EMA 10M CE": "9.38", "EMA 15M CE": "9.68", "ST 5M CE": "11.95", "ST 10M CE": "18.82", "ST 15M CE": "21.36", "Strike": "22600.0", "Last Update Time PE": "11:44:46", "Symbol PE": "NFO:NIFTY2430722600PE", "LTP PE": "0.0", "RSI 5M PE": "41.18", "RSI 10M PE": "36.27", "RSI 15M PE": "34.06", "VWAP 5M PE": "121.77", "VWAP 10M PE": "121.72", "VWAP 15M PE": "124.86", "EMA 5M PE": "110.59", "EMA 10M PE": "121.52", "EMA 15M PE": "142.71", "ST 5M PE": "150.39", "ST 10M PE": "183.36", "ST 15M PE": "214.46"}, {"Last Update Time CE": "11:44:47", "Symbol CE": "NFO:NIFTY2430722650CE", "LTP CE": "0.0", "RSI 5M CE": "43.01", "RSI 10M CE": "44.27", "RSI 15M CE": "43.73", "VWAP 5M CE": "5.07", "VWAP 10M CE": "5.2", "VWAP 15M CE": "5.03", "EMA 5M CE": "3.8", "EMA 10M CE": "4.89", "EMA 15M CE": "5.22", "ST 5M CE": "6.47", "ST 10M CE": "10.57", "ST 15M CE": "12.24", "Strike": "22650.0", "Last Update Time PE": "11:44:48", "Symbol PE": "NFO:NIFTY2430722650PE", "LTP PE": "0.0", "RSI 5M PE": "41.94", "RSI 10M PE": "37.57", "RSI 15M PE": "35.36", "VWAP 5M PE": "167.69", "VWAP 10M PE": "167.34", "VWAP 15M PE": "170.7", "EMA 5M PE": "156.87", "EMA 10M PE": "166.98", "EMA 15M PE": "188.35", "ST 5M PE": "200.28", "ST 10M PE": "235.33", "ST 15M PE": "266.07"}, {"Last Update Time CE": "11:44:49", "Symbol CE": "NFO:NIFTY2430722700CE", "LTP CE": "0.0", "RSI 5M CE": "41.83", "RSI 10M CE": "42.95", "RSI 15M CE": "42.4", "VWAP 5M CE": "2.95", "VWAP 10M CE": "3.03", "VWAP 15M CE": "2.94", "EMA 5M CE": "2.05", "EMA 10M CE": "2.65", "EMA 15M CE": "2.88", "ST 5M CE": "3.59", "ST 10M CE": "5.91", "ST 15M CE": "6.89", "Strike": "22700.0", "Last Update Time PE": "11:44:50", "Symbol PE": "NFO:NIFTY2430722700PE", "LTP PE": "0.0", "RSI 5M PE": "42.56", "RSI 10M PE": "37.82", "RSI 15M PE": "35.93", "VWAP 5M PE": "214.25", "VWAP 10M PE": "213.88", "VWAP 15M PE": "216.95", "EMA 5M PE": "205.08", "EMA 10M PE": "214.58", "EMA 15M PE": "235.99", "ST 5M PE": "250.2", "ST 10M PE": "286.22", "ST 15M PE": "317.86"}, {"Last Update Time CE": "11:44:51", "Symbol CE": "NFO:NIFTY2430722750CE", "LTP CE": "0.0", "RSI 5M CE": "38.59", "RSI 10M CE": "40.62", "RSI 15M CE": "39.07", "VWAP 5M CE": "1.63", "VWAP 10M CE": "1.65", "VWAP 15M CE": "1.63", "EMA 5M CE": "1.13", "EMA 10M CE": "1.47", "EMA 15M CE": "1.66", "ST 5M CE": "1.99", "ST 10M CE": "2.9", "ST 15M CE": "3.53", "Strike": "22750.0", "Last Update Time PE": "11:44:52", "Symbol PE": "NFO:NIFTY2430722750PE", "LTP PE": "0.0", "RSI 5M PE": "42.58", "RSI 10M PE": "38.54", "RSI 15M PE": "36.04", "VWAP 5M PE": "263.13", "VWAP 10M PE": "262.64", "VWAP 15M PE": "266.35", "EMA 5M PE": "254.11", "EMA 10M PE": "263.39", "EMA 15M PE": "284.82", "ST 5M PE": "231.21", "ST 10M PE": "328.99", "ST 15M PE": "358.34"}, {"Last Update Time CE": "11:44:53", "Symbol CE": "NFO:NIFTY2430722800CE", "LTP CE": "0.0", "RSI 5M CE": "36.42", "RSI 10M CE": "38.91", "RSI 15M CE": "35.95", "VWAP 5M CE": "1.1", "VWAP 10M CE": "1.1", "VWAP 15M CE": "1.09", "EMA 5M CE": "0.76", "EMA 10M CE": "0.95", "EMA 15M CE": "1.08", "ST 5M CE": "1.11", "ST 10M CE": "1.61", "ST 15M CE": "2.01", "Strike": "22800.0", "Last Update Time PE": "11:44:54", "Symbol PE": "NFO:NIFTY2430722800PE", "LTP PE": "0.0", "RSI 5M PE": "42.57", "RSI 10M PE": "38.51", "RSI 15M PE": "36.66", "VWAP 5M PE": "313.09", "VWAP 10M PE": "312.95", "VWAP 15M PE": "316.66", "EMA 5M PE": "303.97", "EMA 10M PE": "312.93", "EMA 15M PE": "334.0", "ST 5M PE": "281.13", "ST 10M PE": "380.71", "ST 15M PE": "410.79"}]