[{"Last Update Time CE": "11:31:36", "Symbol CE": "NFO:NIFTY2380319450CE", "LTP CE": "304.65", "RSI 5M CE": "76.36", "RSI 10M CE": "65.83", "RSI 15M CE": "65.81", "VWAP 5M CE": "246.41", "VWAP 10M CE": "245.54", "VWAP 15M CE": "248.27", "EMA 5M CE": "274.76", "EMA 10M CE": "259.99", "EMA 15M CE": "256.55", "ST 5M CE": "262.41", "ST 10M CE": "227.22", "ST 15M CE": "220.51", "Strike": "19450.0", "Last Update Time PE": "11:31:37", "Symbol PE": "NFO:NIFTY2380319450PE", "LTP PE": "12.8", "RSI 5M PE": "26.85", "RSI 10M PE": "30.72", "RSI 15M PE": "30.39", "VWAP 5M PE": "20.49", "VWAP 10M PE": "20.57", "VWAP 15M PE": "20.02", "EMA 5M PE": "15.31", "EMA 10M PE": "18.88", "EMA 15M PE": "21.32", "ST 5M PE": "18.03", "ST 10M PE": "24.99", "ST 15M PE": "28.27"}, {"Last Update Time CE": "11:31:38", "Symbol CE": "NFO:NIFTY2380319500CE", "LTP CE": "260.8", "RSI 5M CE": "75.39", "RSI 10M CE": "65.14", "RSI 15M CE": "65.46", "VWAP 5M CE": "208.4", "VWAP 10M CE": "207.32", "VWAP 15M CE": "209.59", "EMA 5M CE": "231.79", "EMA 10M CE": "218.5", "EMA 15M CE": "215.65", "ST 5M CE": "219.35", "ST 10M CE": "186.93", "ST 15M CE": "180.84", "Strike": "19500.0", "Last Update Time PE": "11:31:39", "Symbol PE": "NFO:NIFTY2380319500PE", "LTP PE": "18.0", "RSI 5M PE": "27.02", "RSI 10M PE": "30.93", "RSI 15M PE": "30.91", "VWAP 5M PE": "29.02", "VWAP 10M PE": "29.09", "VWAP 15M PE": "28.42", "EMA 5M PE": "22.12", "EMA 10M PE": "27.02", "EMA 15M PE": "30.06", "ST 5M PE": "25.93", "ST 10M PE": "35.42", "ST 15M PE": "39.58"}, {"Last Update Time CE": "11:31:41", "Symbol CE": "NFO:NIFTY2380319550CE", "LTP CE": "217.5", "RSI 5M CE": "75.6", "RSI 10M CE": "64.51", "RSI 15M CE": "64.94", "VWAP 5M CE": "169.92", "VWAP 10M CE": "169.32", "VWAP 15M CE": "171.22", "EMA 5M CE": "190.87", "EMA 10M CE": "179.11", "EMA 15M CE": "177.02", "ST 5M CE": "179.54", "ST 10M CE": "150.73", "ST 15M CE": "145.45", "Strike": "19550.0", "Last Update Time PE": "11:31:42", "Symbol PE": "NFO:NIFTY2380319550PE", "LTP PE": "25.2", "RSI 5M PE": "26.31", "RSI 10M PE": "31.04", "RSI 15M PE": "30.62", "VWAP 5M PE": "40.39", "VWAP 10M PE": "40.66", "VWAP 15M PE": "39.74", "EMA 5M PE": "31.11", "EMA 10M PE": "37.52", "EMA 15M PE": "41.35", "ST 5M PE": "36.01", "ST 10M PE": "48.67", "ST 15M PE": "53.66"}, {"Last Update Time CE": "11:31:43", "Symbol CE": "NFO:NIFTY2380319600CE", "LTP CE": "177.55", "RSI 5M CE": "74.95", "RSI 10M CE": "63.82", "RSI 15M CE": "64.27", "VWAP 5M CE": "134.3", "VWAP 10M CE": "133.64", "VWAP 15M CE": "135.54", "EMA 5M CE": "153.14", "EMA 10M CE": "143.06", "EMA 15M CE": "141.75", "ST 5M CE": "142.73", "ST 10M CE": "117.1", "ST 15M CE": "112.62", "Strike": "19600.0", "Last Update Time PE": "11:31:44", "Symbol PE": "NFO:NIFTY2380319600PE", "LTP PE": "35.15", "RSI 5M PE": "26.33", "RSI 10M PE": "31.28", "RSI 15M PE": "30.33", "VWAP 5M PE": "56.06", "VWAP 10M PE": "56.39", "VWAP 15M PE": "54.96", "EMA 5M PE": "43.59", "EMA 10M PE": "51.7", "EMA 15M PE": "56.23", "ST 5M PE": "49.94", "ST 10M PE": "65.94", "ST 15M PE": "71.7"}, {"Last Update Time CE": "11:31:45", "Symbol CE": "NFO:NIFTY2380319650CE", "LTP CE": "141.55", "RSI 5M CE": "75.69", "RSI 10M CE": "63.27", "RSI 15M CE": "63.55", "VWAP 5M CE": "105.6", "VWAP 10M CE": "104.69", "VWAP 15M CE": "106.37", "EMA 5M CE": "119.8", "EMA 10M CE": "111.36", "EMA 15M CE": "110.57", "ST 5M CE": "110.85", "ST 10M CE": "88.83", "ST 15M CE": "85.22", "Strike": "19650.0", "Last Update Time PE": "11:31:46", "Symbol PE": "NFO:NIFTY2380319650PE", "LTP PE": "49.3", "RSI 5M PE": "25.76", "RSI 10M PE": "31.38", "RSI 15M PE": "30.16", "VWAP 5M PE": "73.16", "VWAP 10M PE": "73.55", "VWAP 15M PE": "72.15", "EMA 5M PE": "59.98", "EMA 10M PE": "69.83", "EMA 15M PE": "74.97", "ST 5M PE": "67.43", "ST 10M PE": "87.22", "ST 15M PE": "93.87"}, {"Last Update Time CE": "11:31:47", "Symbol CE": "NFO:NIFTY2380319700CE", "LTP CE": "108.0", "RSI 5M CE": "75.48", "RSI 10M CE": "62.29", "RSI 15M CE": "62.62", "VWAP 5M CE": "81.55", "VWAP 10M CE": "80.26", "VWAP 15M CE": "82.2", "EMA 5M CE": "90.9", "EMA 10M CE": "84.22", "EMA 15M CE": "83.98", "ST 5M CE": "83.34", "ST 10M CE": "65.23", "ST 15M CE": "62.49", "Strike": "19700.0", "Last Update Time PE": "11:31:48", "Symbol PE": "NFO:NIFTY2380319700PE", "LTP PE": "67.55", "RSI 5M PE": "26.18", "RSI 10M PE": "31.6", "RSI 15M PE": "30.24", "VWAP 5M PE": "92.58", "VWAP 10M PE": "93.71", "VWAP 15M PE": "91.67", "EMA 5M PE": "80.99", "EMA 10M PE": "92.54", "EMA 15M PE": "98.2", "ST 5M PE": "89.6", "ST 10M PE": "113.48", "ST 15M PE": "120.77"}, {"Last Update Time CE": "11:31:49", "Symbol CE": "NFO:NIFTY2380319750CE", "LTP CE": "79.9", "RSI 5M CE": "75.63", "RSI 10M CE": "61.17", "RSI 15M CE": "61.33", "VWAP 5M CE": "59.71", "VWAP 10M CE": "58.27", "VWAP 15M CE": "60.23", "EMA 5M CE": "66.25", "EMA 10M CE": "61.25", "EMA 15M CE": "61.45", "ST 5M CE": "60.34", "ST 10M CE": "45.86", "ST 15M CE": "43.8", "Strike": "19750.0", "Last Update Time PE": "11:31:50", "Symbol PE": "NFO:NIFTY2380319750PE", "LTP PE": "90.55", "RSI 5M PE": "25.09", "RSI 10M PE": "31.29", "RSI 15M PE": "30.8", "VWAP 5M PE": "119.94", "VWAP 10M PE": "121.43", "VWAP 15M PE": "118.83", "EMA 5M PE": "106.57", "EMA 10M PE": "119.78", "EMA 15M PE": "125.87", "ST 5M PE": "116.31", "ST 10M PE": "144.09", "ST 15M PE": "152.14"}, {"Last Update Time CE": "11:31:51", "Symbol CE": "NFO:NIFTY2380319800CE", "LTP CE": "57.6", "RSI 5M CE": "74.48", "RSI 10M CE": "58.8", "RSI 15M CE": "59.27", "VWAP 5M CE": "41.86", "VWAP 10M CE": "40.96", "VWAP 15M CE": "42.23", "EMA 5M CE": "46.93", "EMA 10M CE": "43.55", "EMA 15M CE": "44.09", "ST 5M CE": "42.23", "ST 10M CE": "31.3", "ST 15M CE": "29.76", "Strike": "19800.0", "Last Update Time PE": "11:31:52", "Symbol PE": "NFO:NIFTY2380319800PE", "LTP PE": "117.95", "RSI 5M PE": "25.55", "RSI 10M PE": "31.79", "RSI 15M PE": "30.67", "VWAP 5M PE": "155.78", "VWAP 10M PE": "157.45", "VWAP 15M PE": "154.49", "EMA 5M PE": "136.95", "EMA 10M PE": "151.68", "EMA 15M PE": "158.09", "ST 5M PE": "148.2", "ST 10M PE": "179.21", "ST 15M PE": "187.67"}, {"Last Update Time CE": "11:31:53", "Symbol CE": "NFO:NIFTY2380319850CE", "LTP CE": "39.85", "RSI 5M CE": "73.87", "RSI 10M CE": "56.3", "RSI 15M CE": "56.39", "VWAP 5M CE": "28.67", "VWAP 10M CE": "28.07", "VWAP 15M CE": "29.01", "EMA 5M CE": "31.96", "EMA 10M CE": "29.85", "EMA 15M CE": "30.57", "ST 5M CE": "28.41", "ST 10M CE": "20.43", "ST 15M CE": "19.22", "Strike": "19850.0", "Last Update Time PE": "11:31:54", "Symbol PE": "NFO:NIFTY2380319850PE", "LTP PE": "150.0", "RSI 5M PE": "25.33", "RSI 10M PE": "31.89", "RSI 15M PE": "31.1", "VWAP 5M PE": "188.6", "VWAP 10M PE": "190.9", "VWAP 15M PE": "187.33", "EMA 5M PE": "172.1", "EMA 10M PE": "188.17", "EMA 15M PE": "194.72", "ST 5M PE": "183.88", "ST 10M PE": "218.19", "ST 15M PE": "226.77"}, {"Last Update Time CE": "11:31:55", "Symbol CE": "NFO:NIFTY2380319900CE", "LTP CE": "26.45", "RSI 5M CE": "72.63", "RSI 10M CE": "52.86", "RSI 15M CE": "52.87", "VWAP 5M CE": "18.94", "VWAP 10M CE": "18.59", "VWAP 15M CE": "19.15", "EMA 5M CE": "20.9", "EMA 10M CE": "19.78", "EMA 15M CE": "20.57", "ST 5M CE": "18.24", "ST 10M CE": "23.42", "ST 15M CE": "27.69", "Strike": "19900.0", "Last Update Time PE": "11:31:56", "Symbol PE": "NFO:NIFTY2380319900PE", "LTP PE": "186.4", "RSI 5M PE": "24.55", "RSI 10M PE": "31.97", "RSI 15M PE": "31.33", "VWAP 5M PE": "229.2", "VWAP 10M PE": "231.43", "VWAP 15M PE": "227.63", "EMA 5M PE": "211.26", "EMA 10M PE": "228.28", "EMA 15M PE": "234.87", "ST 5M PE": "224.26", "ST 10M PE": "260.62", "ST 15M PE": "269.17"}, {"Last Update Time CE": "11:31:57", "Symbol CE": "NFO:NIFTY2380319950CE", "LTP CE": "16.95", "RSI 5M CE": "70.46", "RSI 10M CE": "47.89", "RSI 15M CE": "48.39", "VWAP 5M CE": "12.13", "VWAP 10M CE": "11.98", "VWAP 15M CE": "12.27", "EMA 5M CE": "13.33", "EMA 10M CE": "12.86", "EMA 15M CE": "13.61", "ST 5M CE": "11.45", "ST 10M CE": "16.69", "ST 15M CE": "18.92", "Strike": "19950.0", "Last Update Time PE": "11:31:58", "Symbol PE": "NFO:NIFTY2380319950PE", "LTP PE": "226.5", "RSI 5M PE": "25.56", "RSI 10M PE": "31.87", "RSI 15M PE": "31.78", "VWAP 5M PE": "279.65", "VWAP 10M PE": "280.67", "VWAP 15M PE": "277.91", "EMA 5M PE": "253.58", "EMA 10M PE": "271.3", "EMA 15M PE": "277.81", "ST 5M PE": "265.23", "ST 10M PE": "304.28", "ST 15M PE": "312.55"}]