[{"Last Update Time CE": "12:15:29", "Symbol CE": "NFO:NIFTY2430722000CE", "LTP CE": "0.0", "RSI 5M CE": "70.11", "RSI 10M CE": "76.41", "RSI 15M CE": "77.17", "VWAP 5M CE": "307.14", "VWAP 10M CE": "306.92", "VWAP 15M CE": "307.43", "EMA 5M CE": "372.1", "EMA 10M CE": "342.78", "EMA 15M CE": "321.21", "ST 5M CE": "352.85", "ST 10M CE": "329.49", "ST 15M CE": "312.47", "Strike": "22000.0", "Last Update Time PE": "12:15:30", "Symbol PE": "NFO:NIFTY2430722000PE", "LTP PE": "0.0", "RSI 5M PE": "30.38", "RSI 10M PE": "28.18", "RSI 15M PE": "29.84", "VWAP 5M PE": "83.49", "VWAP 10M PE": "83.41", "VWAP 15M PE": "83.24", "EMA 5M PE": "71.13", "EMA 10M PE": "80.19", "EMA 15M PE": "89.71", "ST 5M PE": "79.26", "ST 10M PE": "94.12", "ST 15M PE": "109.42"}, {"Last Update Time CE": "12:15:31", "Symbol CE": "NFO:NIFTY2430722050CE", "LTP CE": "0.0", "RSI 5M CE": "69.68", "RSI 10M CE": "76.21", "RSI 15M CE": "77.34", "VWAP 5M CE": "262.91", "VWAP 10M CE": "263.0", "VWAP 15M CE": "263.35", "EMA 5M CE": "334.0", "EMA 10M CE": "306.21", "EMA 15M CE": "285.99", "ST 5M CE": "315.69", "ST 10M CE": "294.27", "ST 15M CE": "278.92", "Strike": "22050.0", "Last Update Time PE": "12:15:32", "Symbol PE": "NFO:NIFTY2430722050PE", "LTP PE": "0.0", "RSI 5M PE": "30.09", "RSI 10M PE": "27.69", "RSI 15M PE": "29.37", "VWAP 5M PE": "100.51", "VWAP 10M PE": "100.55", "VWAP 15M PE": "100.48", "EMA 5M PE": "82.97", "EMA 10M PE": "93.47", "EMA 15M PE": "104.34", "ST 5M PE": "92.04", "ST 10M PE": "108.19", "ST 15M PE": "124.43"}, {"Last Update Time CE": "12:15:33", "Symbol CE": "NFO:NIFTY2430722100CE", "LTP CE": "0.0", "RSI 5M CE": "70.52", "RSI 10M CE": "76.25", "RSI 15M CE": "78.0", "VWAP 5M CE": "232.4", "VWAP 10M CE": "232.37", "VWAP 15M CE": "232.66", "EMA 5M CE": "297.33", "EMA 10M CE": "270.99", "EMA 15M CE": "252.03", "ST 5M CE": "279.94", "ST 10M CE": "259.76", "ST 15M CE": "245.9", "Strike": "22100.0", "Last Update Time PE": "12:15:34", "Symbol PE": "NFO:NIFTY2430722100PE", "LTP PE": "0.0", "RSI 5M PE": "29.4", "RSI 10M PE": "27.07", "RSI 15M PE": "28.76", "VWAP 5M PE": "115.08", "VWAP 10M PE": "115.17", "VWAP 15M PE": "115.0", "EMA 5M PE": "96.22", "EMA 10M PE": "108.31", "EMA 15M PE": "120.51", "ST 5M PE": "106.12", "ST 10M PE": "124.35", "ST 15M PE": "141.92"}, {"Last Update Time CE": "12:15:35", "Symbol CE": "NFO:NIFTY2430722150CE", "LTP CE": "0.0", "RSI 5M CE": "70.41", "RSI 10M CE": "76.35", "RSI 15M CE": "78.25", "VWAP 5M CE": "202.73", "VWAP 10M CE": "202.88", "VWAP 15M CE": "203.51", "EMA 5M CE": "262.95", "EMA 10M CE": "238.35", "EMA 15M CE": "220.71", "ST 5M CE": "246.86", "ST 10M CE": "228.28", "ST 15M CE": "215.89", "Strike": "22150.0", "Last Update Time PE": "12:15:36", "Symbol PE": "NFO:NIFTY2430722150PE", "LTP PE": "0.0", "RSI 5M PE": "29.38", "RSI 10M PE": "27.21", "RSI 15M PE": "28.4", "VWAP 5M PE": "133.93", "VWAP 10M PE": "134.12", "VWAP 15M PE": "134.04", "EMA 5M PE": "111.41", "EMA 10M PE": "125.17", "EMA 15M PE": "138.79", "ST 5M PE": "122.75", "ST 10M PE": "143.2", "ST 15M PE": "162.28"}, {"Last Update Time CE": "12:15:37", "Symbol CE": "NFO:NIFTY2430722200CE", "LTP CE": "0.0", "RSI 5M CE": "69.95", "RSI 10M CE": "76.47", "RSI 15M CE": "78.17", "VWAP 5M CE": "184.9", "VWAP 10M CE": "184.92", "VWAP 15M CE": "185.62", "EMA 5M CE": "229.78", "EMA 10M CE": "206.95", "EMA 15M CE": "190.81", "ST 5M CE": "214.48", "ST 10M CE": "197.77", "ST 15M CE": "186.78", "Strike": "22200.0", "Last Update Time PE": "12:15:38", "Symbol PE": "NFO:NIFTY2430722200PE", "LTP PE": "0.0", "RSI 5M PE": "29.5", "RSI 10M PE": "26.74", "RSI 15M PE": "28.4", "VWAP 5M PE": "148.16", "VWAP 10M PE": "148.27", "VWAP 15M PE": "147.86", "EMA 5M PE": "128.65", "EMA 10M PE": "144.17", "EMA 15M PE": "159.2", "ST 5M PE": "141.13", "ST 10M PE": "162.91", "ST 15M PE": "183.13"}, {"Last Update Time CE": "12:15:39", "Symbol CE": "NFO:NIFTY2430722250CE", "LTP CE": "0.0", "RSI 5M CE": "70.26", "RSI 10M CE": "76.4", "RSI 15M CE": "78.58", "VWAP 5M CE": "165.55", "VWAP 10M CE": "165.44", "VWAP 15M CE": "166.04", "EMA 5M CE": "199.5", "EMA 10M CE": "178.37", "EMA 15M CE": "163.88", "ST 5M CE": "185.24", "ST 10M CE": "170.25", "ST 15M CE": "160.57", "Strike": "22250.0", "Last Update Time PE": "12:15:40", "Symbol PE": "NFO:NIFTY2430722250PE", "LTP PE": "0.0", "RSI 5M PE": "29.04", "RSI 10M PE": "26.4", "RSI 15M PE": "27.9", "VWAP 5M PE": "161.37", "VWAP 10M PE": "161.75", "VWAP 15M PE": "161.19", "EMA 5M PE": "147.9", "EMA 10M PE": "165.21", "EMA 15M PE": "181.7", "ST 5M PE": "161.39", "ST 10M PE": "183.25", "ST 15M PE": "204.94"}, {"Last Update Time CE": "12:15:41", "Symbol CE": "NFO:NIFTY2430722300CE", "LTP CE": "0.0", "RSI 5M CE": "69.65", "RSI 10M CE": "76.25", "RSI 15M CE": "78.72", "VWAP 5M CE": "140.61", "VWAP 10M CE": "140.38", "VWAP 15M CE": "140.72", "EMA 5M CE": "170.27", "EMA 10M CE": "151.12", "EMA 15M CE": "138.13", "ST 5M CE": "157.4", "ST 10M CE": "143.84", "ST 15M CE": "135.42", "Strike": "22300.0", "Last Update Time PE": "12:15:42", "Symbol PE": "NFO:NIFTY2430722300PE", "LTP PE": "0.0", "RSI 5M PE": "28.68", "RSI 10M PE": "26.24", "RSI 15M PE": "27.19", "VWAP 5M PE": "180.04", "VWAP 10M PE": "180.61", "VWAP 15M PE": "180.26", "EMA 5M PE": "169.21", "EMA 10M PE": "188.39", "EMA 15M PE": "206.43", "ST 5M PE": "183.91", "ST 10M PE": "208.86", "ST 15M PE": "233.08"}, {"Last Update Time CE": "12:15:43", "Symbol CE": "NFO:NIFTY2430722350CE", "LTP CE": "0.0", "RSI 5M CE": "69.93", "RSI 10M CE": "76.17", "RSI 15M CE": "79.27", "VWAP 5M CE": "116.69", "VWAP 10M CE": "116.44", "VWAP 15M CE": "116.86", "EMA 5M CE": "143.91", "EMA 10M CE": "126.85", "EMA 15M CE": "115.42", "ST 5M CE": "132.79", "ST 10M CE": "121.07", "ST 15M CE": "114.04", "Strike": "22350.0", "Last Update Time PE": "12:15:44", "Symbol PE": "NFO:NIFTY2430722350PE", "LTP PE": "0.0", "RSI 5M PE": "28.87", "RSI 10M PE": "25.19", "RSI 15M PE": "27.26", "VWAP 5M PE": "204.09", "VWAP 10M PE": "204.75", "VWAP 15M PE": "204.35", "EMA 5M PE": "192.73", "EMA 10M PE": "213.97", "EMA 15M PE": "234.16", "ST 5M PE": "207.8", "ST 10M PE": "230.22", "ST 15M PE": "253.73"}, {"Last Update Time CE": "12:15:45", "Symbol CE": "NFO:NIFTY2430722400CE", "LTP CE": "0.0", "RSI 5M CE": "69.51", "RSI 10M CE": "75.87", "RSI 15M CE": "79.33", "VWAP 5M CE": "95.69", "VWAP 10M CE": "95.57", "VWAP 15M CE": "95.94", "EMA 5M CE": "119.76", "EMA 10M CE": "104.78", "EMA 15M CE": "94.95", "ST 5M CE": "109.8", "ST 10M CE": "99.62", "ST 15M CE": "93.7", "Strike": "22400.0", "Last Update Time PE": "12:15:46", "Symbol PE": "NFO:NIFTY2430722400PE", "LTP PE": "0.0", "RSI 5M PE": "29.3", "RSI 10M PE": "24.99", "RSI 15M PE": "27.82", "VWAP 5M PE": "234.03", "VWAP 10M PE": "234.62", "VWAP 15M PE": "234.04", "EMA 5M PE": "218.85", "EMA 10M PE": "242.22", "EMA 15M PE": "263.69", "ST 5M PE": "235.24", "ST 10M PE": "262.2", "ST 15M PE": "286.99"}, {"Last Update Time CE": "12:15:47", "Symbol CE": "NFO:NIFTY2430722450CE", "LTP CE": "0.0", "RSI 5M CE": "69.32", "RSI 10M CE": "75.38", "RSI 15M CE": "79.18", "VWAP 5M CE": "77.87", "VWAP 10M CE": "77.84", "VWAP 15M CE": "78.14", "EMA 5M CE": "98.71", "EMA 10M CE": "85.79", "EMA 15M CE": "77.54", "ST 5M CE": "90.26", "ST 10M CE": "81.78", "ST 15M CE": "76.9", "Strike": "22450.0", "Last Update Time PE": "12:15:48", "Symbol PE": "NFO:NIFTY2430722450PE", "LTP PE": "0.0", "RSI 5M PE": "28.95", "RSI 10M PE": "25.82", "RSI 15M PE": "26.52", "VWAP 5M PE": "273.71", "VWAP 10M PE": "274.1", "VWAP 15M PE": "273.42", "EMA 5M PE": "247.59", "EMA 10M PE": "272.87", "EMA 15M PE": "295.82", "ST 5M PE": "263.81", "ST 10M PE": "289.47", "ST 15M PE": "311.5"}, {"Last Update Time CE": "12:15:49", "Symbol CE": "NFO:NIFTY2430722500CE", "LTP CE": "0.0", "RSI 5M CE": "68.64", "RSI 10M CE": "74.91", "RSI 15M CE": "79.24", "VWAP 5M CE": "62.08", "VWAP 10M CE": "61.99", "VWAP 15M CE": "62.36", "EMA 5M CE": "79.77", "EMA 10M CE": "68.78", "EMA 15M CE": "61.94", "ST 5M CE": "72.49", "ST 10M CE": "65.24", "ST 15M CE": "61.31", "Strike": "22500.0", "Last Update Time PE": "12:15:50", "Symbol PE": "NFO:NIFTY2430722500PE", "LTP PE": "0.0", "RSI 5M PE": "29.28", "RSI 10M PE": "24.97", "RSI 15M PE": "26.47", "VWAP 5M PE": "306.12", "VWAP 10M PE": "306.76", "VWAP 15M PE": "306.27", "EMA 5M PE": "278.68", "EMA 10M PE": "305.79", "EMA 15M PE": "329.92", "ST 5M PE": "297.62", "ST 10M PE": "327.79", "ST 15M PE": "354.85"}, {"Last Update Time CE": "12:15:51", "Symbol CE": "NFO:NIFTY2430722550CE", "LTP CE": "0.0", "RSI 5M CE": "68.56", "RSI 10M CE": "74.78", "RSI 15M CE": "79.42", "VWAP 5M CE": "47.1", "VWAP 10M CE": "47.19", "VWAP 15M CE": "47.42", "EMA 5M CE": "63.66", "EMA 10M CE": "54.44", "EMA 15M CE": "48.85", "ST 5M CE": "57.57", "ST 10M CE": "51.69", "ST 15M CE": "48.51", "Strike": "22550.0", "Last Update Time PE": "12:15:52", "Symbol PE": "NFO:NIFTY2430722550PE", "LTP PE": "0.0", "RSI 5M PE": "27.96", "RSI 10M PE": "24.54", "RSI 15M PE": "23.07", "VWAP 5M PE": "324.83", "VWAP 10M PE": "325.76", "VWAP 15M PE": "325.24", "EMA 5M PE": "312.54", "EMA 10M PE": "341.64", "EMA 15M PE": "367.0", "ST 5M PE": "327.67", "ST 10M PE": "351.13", "ST 15M PE": "371.4"}, {"Last Update Time CE": "12:15:53", "Symbol CE": "NFO:NIFTY2430722600CE", "LTP CE": "0.0", "RSI 5M CE": "68.63", "RSI 10M CE": "74.24", "RSI 15M CE": "79.43", "VWAP 5M CE": "37.79", "VWAP 10M CE": "37.74", "VWAP 15M CE": "37.98", "EMA 5M CE": "49.88", "EMA 10M CE": "42.4", "EMA 15M CE": "37.93", "ST 5M CE": "44.86", "ST 10M CE": "40.21", "ST 15M CE": "37.88", "Strike": "22600.0", "Last Update Time PE": "12:15:54", "Symbol PE": "NFO:NIFTY2430722600PE", "LTP PE": "0.0", "RSI 5M PE": "29.71", "RSI 10M PE": "24.61", "RSI 15M PE": "26.6", "VWAP 5M PE": "367.18", "VWAP 10M PE": "368.7", "VWAP 15M PE": "368.65", "EMA 5M PE": "348.62", "EMA 10M PE": "379.62", "EMA 15M PE": "406.5", "ST 5M PE": "366.67", "ST 10M PE": "397.07", "ST 15M PE": "425.31"}]