[{"Last Update Time CE": "13:40:31", "Symbol CE": "NFO:NIFTY2420821650CE", "LTP CE": "322.0", "RSI 5M CE": "48.95", "RSI 10M CE": "51.79", "RSI 15M CE": "47.41", "VWAP 5M CE": "312.46", "VWAP 10M CE": "312.41", "VWAP 15M CE": "315.58", "EMA 5M CE": "330.1", "EMA 10M CE": "327.15", "EMA 15M CE": "325.37", "ST 5M CE": "296.37", "ST 10M CE": "384.47", "ST 15M CE": "420.2", "Strike": "21650.0", "Last Update Time PE": "13:40:32", "Symbol PE": "NFO:NIFTY2420821650PE", "LTP PE": "49.0", "RSI 5M PE": "46.95", "RSI 10M PE": "40.7", "RSI 15M PE": "43.47", "VWAP 5M PE": "60.42", "VWAP 10M PE": "60.07", "VWAP 15M PE": "59.12", "EMA 5M PE": "48.37", "EMA 10M PE": "50.67", "EMA 15M PE": "52.97", "ST 5M PE": "57.44", "ST 10M PE": "67.61", "ST 15M PE": "33.85"}, {"Last Update Time CE": "13:40:33", "Symbol CE": "NFO:NIFTY2420821700CE", "LTP CE": "282.35", "RSI 5M CE": "48.11", "RSI 10M CE": "50.76", "RSI 15M CE": "47.04", "VWAP 5M CE": "278.7", "VWAP 10M CE": "279.03", "VWAP 15M CE": "280.96", "EMA 5M CE": "290.85", "EMA 10M CE": "288.67", "EMA 15M CE": "287.44", "ST 5M CE": "256.87", "ST 10M CE": "340.83", "ST 15M CE": "379.14", "Strike": "21700.0", "Last Update Time PE": "13:40:34", "Symbol PE": "NFO:NIFTY2420821700PE", "LTP PE": "60.5", "RSI 5M PE": "47.3", "RSI 10M PE": "41.4", "RSI 15M PE": "44.14", "VWAP 5M PE": "73.04", "VWAP 10M PE": "72.36", "VWAP 15M PE": "71.31", "EMA 5M PE": "59.21", "EMA 10M PE": "61.82", "EMA 15M PE": "64.42", "ST 5M PE": "70.26", "ST 10M PE": "54.78", "ST 15M PE": "40.75"}, {"Last Update Time CE": "13:40:35", "Symbol CE": "NFO:NIFTY2420821750CE", "LTP CE": "246.2", "RSI 5M CE": "47.84", "RSI 10M CE": "50.63", "RSI 15M CE": "46.58", "VWAP 5M CE": "242.56", "VWAP 10M CE": "243.06", "VWAP 15M CE": "245.85", "EMA 5M CE": "254.18", "EMA 10M CE": "252.57", "EMA 15M CE": "251.64", "ST 5M CE": "222.95", "ST 10M CE": "303.77", "ST 15M CE": "338.73", "Strike": "21750.0", "Last Update Time PE": "13:40:36", "Symbol PE": "NFO:NIFTY2420821750PE", "LTP PE": "74.3", "RSI 5M PE": "47.51", "RSI 10M PE": "41.43", "RSI 15M PE": "44.52", "VWAP 5M PE": "87.78", "VWAP 10M PE": "87.43", "VWAP 15M PE": "86.63", "EMA 5M PE": "72.66", "EMA 10M PE": "75.72", "EMA 15M PE": "78.66", "ST 5M PE": "85.9", "ST 10M PE": "65.4", "ST 15M PE": "49.67"}, {"Last Update Time CE": "13:40:37", "Symbol CE": "NFO:NIFTY2420821800CE", "LTP CE": "211.9", "RSI 5M CE": "47.67", "RSI 10M CE": "50.25", "RSI 15M CE": "46.35", "VWAP 5M CE": "211.48", "VWAP 10M CE": "211.14", "VWAP 15M CE": "213.69", "EMA 5M CE": "219.83", "EMA 10M CE": "218.62", "EMA 15M CE": "217.92", "ST 5M CE": "189.66", "ST 10M CE": "260.12", "ST 15M CE": "300.87", "Strike": "21800.0", "Last Update Time PE": "13:40:38", "Symbol PE": "NFO:NIFTY2420821800PE", "LTP PE": "90.6", "RSI 5M PE": "47.94", "RSI 10M PE": "42.28", "RSI 15M PE": "45.14", "VWAP 5M PE": "106.6", "VWAP 10M PE": "105.99", "VWAP 15M PE": "104.77", "EMA 5M PE": "88.3", "EMA 10M PE": "91.75", "EMA 15M PE": "94.92", "ST 5M PE": "103.57", "ST 10M PE": "77.55", "ST 15M PE": "60.05"}, {"Last Update Time CE": "13:40:39", "Symbol CE": "NFO:NIFTY2420821850CE", "LTP CE": "180.35", "RSI 5M CE": "47.58", "RSI 10M CE": "49.69", "RSI 15M CE": "46.04", "VWAP 5M CE": "180.95", "VWAP 10M CE": "181.11", "VWAP 15M CE": "183.28", "EMA 5M CE": "188.38", "EMA 10M CE": "187.38", "EMA 15M CE": "186.98", "ST 5M CE": "160.63", "ST 10M CE": "234.06", "ST 15M CE": "264.82", "Strike": "21850.0", "Last Update Time PE": "13:40:40", "Symbol PE": "NFO:NIFTY2420821850PE", "LTP PE": "108.05", "RSI 5M PE": "48.0", "RSI 10M PE": "42.82", "RSI 15M PE": "45.72", "VWAP 5M PE": "128.85", "VWAP 10M PE": "128.21", "VWAP 15M PE": "126.67", "EMA 5M PE": "106.37", "EMA 10M PE": "110.14", "EMA 15M PE": "113.74", "ST 5M PE": "124.2", "ST 10M PE": "91.79", "ST 15M PE": "72.84"}, {"Last Update Time CE": "13:40:41", "Symbol CE": "NFO:NIFTY2420821900CE", "LTP CE": "154.0", "RSI 5M CE": "47.33", "RSI 10M CE": "49.34", "RSI 15M CE": "45.8", "VWAP 5M CE": "156.32", "VWAP 10M CE": "155.92", "VWAP 15M CE": "157.29", "EMA 5M CE": "159.42", "EMA 10M CE": "158.74", "EMA 15M CE": "158.7", "ST 5M CE": "134.33", "ST 10M CE": "201.61", "ST 15M CE": "230.28", "Strike": "21900.0", "Last Update Time PE": "13:40:42", "Symbol PE": "NFO:NIFTY2420821900PE", "LTP PE": "128.4", "RSI 5M PE": "48.26", "RSI 10M PE": "43.11", "RSI 15M PE": "46.08", "VWAP 5M PE": "147.19", "VWAP 10M PE": "146.84", "VWAP 15M PE": "145.47", "EMA 5M PE": "127.08", "EMA 10M PE": "131.34", "EMA 15M PE": "135.11", "ST 5M PE": "147.46", "ST 10M PE": "107.5", "ST 15M PE": "86.76"}, {"Last Update Time CE": "13:40:43", "Symbol CE": "NFO:NIFTY2420821950CE", "LTP CE": "128.55", "RSI 5M CE": "46.92", "RSI 10M CE": "48.77", "RSI 15M CE": "45.32", "VWAP 5M CE": "133.63", "VWAP 10M CE": "133.04", "VWAP 15M CE": "134.08", "EMA 5M CE": "133.2", "EMA 10M CE": "133.01", "EMA 15M CE": "133.19", "ST 5M CE": "110.44", "ST 10M CE": "172.99", "ST 15M CE": "197.98", "Strike": "21950.0", "Last Update Time PE": "13:40:44", "Symbol PE": "NFO:NIFTY2420821950PE", "LTP PE": "152.05", "RSI 5M PE": "48.54", "RSI 10M PE": "43.49", "RSI 15M PE": "46.61", "VWAP 5M PE": "169.43", "VWAP 10M PE": "169.66", "VWAP 15M PE": "168.85", "EMA 5M PE": "151.0", "EMA 10M PE": "155.64", "EMA 15M PE": "159.72", "ST 5M PE": "174.2", "ST 10M PE": "125.98", "ST 15M PE": "103.77"}, {"Last Update Time CE": "13:40:45", "Symbol CE": "NFO:NIFTY2420822000CE", "LTP CE": "105.95", "RSI 5M CE": "46.42", "RSI 10M CE": "48.07", "RSI 15M CE": "44.86", "VWAP 5M CE": "111.07", "VWAP 10M CE": "110.77", "VWAP 15M CE": "111.83", "EMA 5M CE": "110.07", "EMA 10M CE": "110.24", "EMA 15M CE": "110.7", "ST 5M CE": "89.93", "ST 10M CE": "147.03", "ST 15M CE": "167.59", "Strike": "22000.0", "Last Update Time PE": "13:40:46", "Symbol PE": "NFO:NIFTY2420822000PE", "LTP PE": "179.05", "RSI 5M PE": "48.58", "RSI 10M PE": "43.83", "RSI 15M PE": "47.11", "VWAP 5M PE": "198.9", "VWAP 10M PE": "198.33", "VWAP 15M PE": "196.49", "EMA 5M PE": "177.99", "EMA 10M PE": "183.05", "EMA 15M PE": "187.23", "ST 5M PE": "203.11", "ST 10M PE": "149.94", "ST 15M PE": "122.99"}, {"Last Update Time CE": "13:40:47", "Symbol CE": "NFO:NIFTY2420822050CE", "LTP CE": "86.2", "RSI 5M CE": "46.13", "RSI 10M CE": "47.7", "RSI 15M CE": "44.41", "VWAP 5M CE": "92.06", "VWAP 10M CE": "91.65", "VWAP 15M CE": "92.61", "EMA 5M CE": "89.94", "EMA 10M CE": "90.38", "EMA 15M CE": "91.02", "ST 5M CE": "72.24", "ST 10M CE": "123.46", "ST 15M CE": "140.44", "Strike": "22050.0", "Last Update Time PE": "13:40:49", "Symbol PE": "NFO:NIFTY2420822050PE", "LTP PE": "210.6", "RSI 5M PE": "48.98", "RSI 10M PE": "44.08", "RSI 15M PE": "47.6", "VWAP 5M PE": "229.02", "VWAP 10M PE": "229.89", "VWAP 15M PE": "229.14", "EMA 5M PE": "207.99", "EMA 10M PE": "213.08", "EMA 15M PE": "217.55", "ST 5M PE": "235.4", "ST 10M PE": "186.78", "ST 15M PE": "150.19"}, {"Last Update Time CE": "13:40:49", "Symbol CE": "NFO:NIFTY2420822100CE", "LTP CE": "68.4", "RSI 5M CE": "45.72", "RSI 10M CE": "47.1", "RSI 15M CE": "44.14", "VWAP 5M CE": "74.99", "VWAP 10M CE": "74.67", "VWAP 15M CE": "76.01", "EMA 5M CE": "72.62", "EMA 10M CE": "73.23", "EMA 15M CE": "73.93", "ST 5M CE": "57.43", "ST 10M CE": "101.45", "ST 15M CE": "116.52", "Strike": "22100.0", "Last Update Time PE": "13:40:50", "Symbol PE": "NFO:NIFTY2420822100PE", "LTP PE": "243.7", "RSI 5M PE": "49.03", "RSI 10M PE": "44.69", "RSI 15M PE": "47.9", "VWAP 5M PE": "263.51", "VWAP 10M PE": "264.17", "VWAP 15M PE": "262.89", "EMA 5M PE": "240.78", "EMA 10M PE": "246.27", "EMA 15M PE": "250.7", "ST 5M PE": "270.5", "ST 10M PE": "217.23", "ST 15M PE": "175.87"}, {"Last Update Time CE": "13:40:52", "Symbol CE": "NFO:NIFTY2420822150CE", "LTP CE": "54.85", "RSI 5M CE": "45.31", "RSI 10M CE": "46.39", "RSI 15M CE": "43.76", "VWAP 5M CE": "61.04", "VWAP 10M CE": "60.58", "VWAP 15M CE": "61.69", "EMA 5M CE": "57.98", "EMA 10M CE": "58.72", "EMA 15M CE": "59.57", "ST 5M CE": "45.19", "ST 10M CE": "82.18", "ST 15M CE": "95.41", "Strike": "22150.0", "Last Update Time PE": "13:40:52", "Symbol PE": "NFO:NIFTY2420822150PE", "LTP PE": "279.4", "RSI 5M PE": "49.16", "RSI 10M PE": "44.1", "RSI 15M PE": "48.69", "VWAP 5M PE": "297.34", "VWAP 10M PE": "299.14", "VWAP 15M PE": "298.37", "EMA 5M PE": "275.61", "EMA 10M PE": "281.11", "EMA 15M PE": "286.31", "ST 5M PE": "258.43", "ST 10M PE": "249.23", "ST 15M PE": "205.94"}]